aecSpace/__init__.py
aecSpace/aecColor.py
aecSpace/aecCompass.py
aecSpace/aecCorridor.py
aecSpace/aecFloor-new.py
aecSpace/aecFloor.py
aecSpace/aecGeometry.py
aecSpace/aecPoint.py
aecSpace/aecShaper.py
aecSpace/aecSpace.py
aecSpace/aecSpaceDrawOCC.py
aecSpace/aecSpaceDrawPlotly.py
aecSpace/aecSpaceGrid.py
aecSpace/aecSpaceGroup.py
aecSpace/aecSpacer.py
aecSpace/aecValid.py
aecSpace-0.7.1.dist-info/METADATA
aecSpace-0.7.1.dist-info/RECORD
aecSpace-0.7.1.dist-info/WHEEL
aecSpace-0.7.1.dist-info/top_level.txt
